qm/__init__.py
qm/main.py
qm/commands/__init__.py
qm/commands/add.py
qm/commands/build.py
qm/commands/init.py
qm/commands/lint.py
qm/commands/logs.py
qm/commands/output.py
qm/commands/run.py
qm/commands/test.py
qm/commands/validate.py
quantum_machine-3.0.0.dist-info/licenses/LICENSE
quantum_machine-3.0.0.dist-info/METADATA
quantum_machine-3.0.0.dist-info/WHEEL
quantum_machine-3.0.0.dist-info/entry_points.txt
quantum_machine-3.0.0.dist-info/top_level.txt
quantum_machine-3.0.0.dist-info/RECORD
