Metadata-Version: 2.4
Name: quantum-machine
Version: 3.0.0
Summary: Quantum-CLI: A powerful CLI to build, run, and test Quantum Machines.
Home-page: https://www.quantumdatalytica.com
Author: Quantum Datalytica LLC
Author-email: itsupport@quantumdatalytica.com
Classifier: Programming Language :: Python :: 3
Classifier: License :: OSI Approved :: MIT License
Classifier: Operating System :: OS Independent
Requires-Python: >=3.7
License-File: LICENSE
Requires-Dist: typer
Requires-Dist: rich
Requires-Dist: flake8
Requires-Dist: pyyaml
Dynamic: author
Dynamic: author-email
Dynamic: classifier
Dynamic: description
Dynamic: description-content-type
Dynamic: home-page
Dynamic: license-file
Dynamic: requires-dist
Dynamic: requires-python
Dynamic: summary
